DTSUMO/__init__.py
DTSUMO-0.2.1.dist-info/METADATA
DTSUMO-0.2.1.dist-info/WHEEL
DTSUMO-0.2.1.dist-info/license.txt
DTSUMO-0.2.1.dist-info/top_level.txt
DTSUMO-0.2.1.dist-info/RECORD
