Metadata-Version: 2.1
Name: DTSUMO
Version: 0.2.1
Summary: A small example package
Home-page: https://github.com/wkgj
Author: Example Author
Author-email: weikeguojing@gmail.com
License: UNKNOWN
Platform: UNKNOWN
Classifier: Programming Language :: Python :: 3
Classifier: License :: OSI Approved :: MIT License
Classifier: Operating System :: OS Independent
License-File: license.txt
